dev_mapper-0.0.4.data/data/VERSION
devmapper/__init__.py
devmapper/devmap.py
devmapper/mapper.py
devmapper/test/__init__.py
devmapper/test/test_mapper.py
dev_mapper-0.0.4.dist-info/METADATA
dev_mapper-0.0.4.dist-info/WHEEL
dev_mapper-0.0.4.dist-info/top_level.txt
dev_mapper-0.0.4.dist-info/RECORD
