Metadata-Version: 2.1
Name: dev-mapper
Version: 0.0.4
Summary: Device Mapper to convert the sys-pci-address to a device file
Home-page: https://github.com/peanutstars/py-dev-mapper
Author: HyunSuk Lee
Author-email: peanutstars.job@gmail.com
License: UNKNOWN
Keywords: dev path convert
Platform: UNKNOWN
Classifier: Environment :: Console
Classifier: Intended Audience :: Developers
Classifier: Intended Audience :: Manufacturing
Classifier: Operating System :: POSIX :: Linux
Classifier: Topic :: System :: Operating System Kernels :: Linux
Classifier: Programming Language :: Python :: 2
Classifier: Programming Language :: Python :: 2.7
Classifier: Programming Language :: Python :: 3
Classifier: Programming Language :: Python :: 3.6
